epilogos/__init__.py
epilogos/expected.py
epilogos/expectedCombination.py
epilogos/filter_regions.py
epilogos/helpers.py
epilogos/plotRegion.py
epilogos/roiAndVisualPairwise.py
epilogos/roiSingle.py
epilogos/run.py
epilogos/scores.py
epilogos/similaritySearch_calc.py
epilogos/similaritySearch_max_mean.py
epilogos/similaritySearch_run.py
epilogos/similaritySearch_write.py
epilogos-0.1.2.data/scripts/download_example_data.sh
epilogos-0.1.2.data/scripts/preprocess_data_ChromHMM.sh
epilogos-0.1.2.dist-info/LICENSE
epilogos-0.1.2.dist-info/METADATA
epilogos-0.1.2.dist-info/WHEEL
epilogos-0.1.2.dist-info/entry_points.txt
epilogos-0.1.2.dist-info/top_level.txt
epilogos-0.1.2.dist-info/RECORD
