Metadata-Version: 2.1
Name: epilogos
Version: 0.1.2
Summary: Information-theoretic navigation of multi-tissue functional genomic annotations
Home-page: https://github.com/meuleman/epilogos
Author: Wouter Meuleman, Jacob Quon, Alex Reynolds, Eric Rynes
Author-email: wouter@meuleman.org
License: LICENSE.txt
License-File: LICENSE
Requires-Dist: click (==8.1.3)
Requires-Dist: matplotlib (==3.6.1)
Requires-Dist: numpy (==1.23.4)
Requires-Dist: pandas (==1.5.1)
Requires-Dist: pysam (==0.19.1)
Requires-Dist: scikit-learn (==1.1.3)
Requires-Dist: scipy (==1.9.3)
Requires-Dist: statsmodels (==0.13.2)
Requires-Dist: natsort (==8.2.0)
Requires-Dist: pyranges (==0.0.117)
Requires-Dist: rich (==12.6.0)
